pyprefab/__init__.py
pyprefab/__main__.py
pyprefab/cli.py
pyprefab/config.py
pyprefab/config.toml
pyprefab/exceptions.py
pyprefab/logger.py
pyprefab/templates/.gitignore.j2
pyprefab/templates/.pre-commit-config.yaml.j2
pyprefab/templates/.python-version
pyprefab/templates/CHANGELOG.md.j2
pyprefab/templates/CONTRIBUTING.md.j2
pyprefab/templates/LICENSE.j2
pyprefab/templates/README.md.j2
pyprefab/templates/pyproject.toml.j2
pyprefab/templates/.github/dependabot.yaml.j2
pyprefab/templates/.github/workflows/ci.yaml.j2
pyprefab/templates/.github/workflows/publish-pypi.yaml.j2
pyprefab/templates/docs/source/CHANGELOG.md.j2
pyprefab/templates/docs/source/CONTRIBUTING.md.j2
pyprefab/templates/docs/source/conf.py.j2
pyprefab/templates/docs/source/index.rst.j2
pyprefab/templates/docs/source/readme.md.j2
pyprefab/templates/docs/source/usage.md.j2
pyprefab/templates/docs/source/_static/custom.css.j2
pyprefab/templates/src/{{ package_name }}/__init__.py.j2
pyprefab/templates/src/{{ package_name }}/__main__.py.j2
pyprefab/templates/src/{{ package_name }}/app.py.j2
pyprefab/templates/src/{{ package_name }}/logger.py.j2
pyprefab/templates/test/test_app.py
pyprefab-0.5.8.dist-info/licenses/LICENSE
pyprefab-0.5.8.dist-info/METADATA
pyprefab-0.5.8.dist-info/WHEEL
pyprefab-0.5.8.dist-info/entry_points.txt
pyprefab-0.5.8.dist-info/top_level.txt
pyprefab-0.5.8.dist-info/RECORD
