Metadata-Version: 2.4
Name: pyprefab
Version: 0.5.8
Summary: Python application template for personal use
Author-email: Becky Sweger <bsweger@gmail.com>
License-Expression: MIT
Project-URL: Documentation, https://bsweger.github.io/pyprefab/index.html
Project-URL: Repository, https://github.com/bsweger/pyprefab.git
Project-URL: Changelog, https://github.com/bsweger/pyprefab/blob/main/CHANGELOG.md
Classifier: Development Status :: 4 - Beta
Classifier: Programming Language :: Python :: 3 :: Only
Classifier: Programming Language :: Python :: 3.11
Classifier: Programming Language :: Python :: 3.12
Classifier: Programming Language :: Python :: 3.13
Classifier: Programming Language :: Python :: 3.14
Requires-Python: >=3.11
License-File: LICENSE
Requires-Dist: structlog
Requires-Dist: rich
Requires-Dist: typer
Requires-Dist: jinja2>=3.1.5
Dynamic: license-file
